setuptools_git_ver.py
setuptools_git_ver-1.0.4.dist-info/LICENSE
setuptools_git_ver-1.0.4.dist-info/METADATA
setuptools_git_ver-1.0.4.dist-info/WHEEL
setuptools_git_ver-1.0.4.dist-info/entry_points.txt
setuptools_git_ver-1.0.4.dist-info/top_level.txt
setuptools_git_ver-1.0.4.dist-info/RECORD
