Metadata-Version: 2.1
Name: setuptools-git-ver
Version: 1.0.4
Summary: Automatically set package version using git tag/hash
Home-page: https://github.com/camas/setuptools-git-ver
Author: Camas
Author-email: camas@hotmail.co.uk
License: UNKNOWN
Keywords: setuptools git version-control
Platform: UNKNOWN
Classifier: Framework :: Setuptools Plugin
Classifier: Intended Audience :: Developers
Classifier: Programming Language :: Python :: 3
Classifier: License :: OSI Approved :: MIT License
Classifier: Operating System :: OS Independent
Requires-Python: >=3.7
Requires-Dist: setuptools
